alteia_cli/__init__.py
alteia_cli/__main__.py
alteia_cli/color_manager.py
alteia_cli/config.py
alteia_cli/custom_analytics/__init__.py
alteia_cli/custom_analytics/analytics.py
alteia_cli/custom_analytics/configurations.py
alteia_cli/custom_analytics/credentials.py
alteia_cli/custom_analytics/products.py
alteia_cli/custom_analytics/share/analytic_schema.yaml
alteia_cli/custom_analytics/utils.py
alteia_cli/loader.py
alteia_cli/main.py
alteia_cli/plugins/__init__.py
alteia_cli/sdk.py
alteia_cli/utils.py
alteia_cli-1.11.2.dist-info/METADATA
alteia_cli-1.11.2.dist-info/WHEEL
alteia_cli-1.11.2.dist-info/entry_points.txt
alteia_cli-1.11.2.dist-info/RECORD
