Metadata-Version: 2.1
Name: alteia-cli
Version: 1.11.2
Summary: CLI for Alteia
License: MIT
Keywords: cli,alteia
Author: Alteia Backend Team
Author-email: backend-team@alteia.com
Requires-Python: >=3.11.0,<4.0.0
Classifier: License :: OSI Approved :: MIT License
Classifier: Programming Language :: Python :: 3
Classifier: Programming Language :: Python :: 3.11
Requires-Dist: alteia (>=2.16.0,<3.0.0)
Requires-Dist: click (<=8.1.8)
Requires-Dist: click_spinner (>=0.1.8,<0.2.0)
Requires-Dist: jsonschema (>=3.0.0,<5.0.0)
Requires-Dist: pyinquirer (>=1.0.3,<2.0.0)
Requires-Dist: pyyaml (>=5.0.0,<7.0.0)
Requires-Dist: semver (>=3.0.2,<4.0.0)
Requires-Dist: tabulate (>=0.8.9)
Requires-Dist: typer (>=0.15.1,<0.16.0)
